[{
    "score": 5,
    "description": "Muy comodo para hacer largas distancias",
    "user": "roberto",
    "dateTime": "2020-07-25 18:03:52"
},
{
    "score": 5,
    "description": "Se desempeña bien tanto en ciudad como en carretera",
    "user": "rodrigo",
    "dateTime": "2020-08-17 13:42:18"
},
{
    "score": 4,
    "description": "Muy conforme, aunque su precio es un poco elevado para lo que ofrece",
    "user": "mariela",
    "dateTime": "2020-09-14 09:05:13"
},
{
    "score": 5,
    "description": "Esta genial!",
    "user": "agustin",
    "dateTime": "2020-11-21 15:05:22"
}]